shopyo_auth/__init__.py
shopyo_auth/decorators.py
shopyo_auth/forms.py
shopyo_auth/info.json
shopyo_auth/models.py
shopyo_auth/upload.py
shopyo_auth/view.py
shopyo_auth/static/style.css
shopyo_auth/templates/shopyo_auth/forgot_password.html
shopyo_auth/templates/shopyo_auth/login.html
shopyo_auth/templates/shopyo_auth/register.html
shopyo_auth/templates/shopyo_auth/reset_password.html
shopyo_auth/templates/shopyo_auth/shop_login.html
shopyo_auth/templates/shopyo_auth/unconfirmed.html
shopyo_auth/templates/shopyo_auth/blocks/login_form.html
shopyo_auth/templates/shopyo_auth/blocks/register_form.html
shopyo_auth/templates/shopyo_auth/emails/activate_user.html
shopyo_auth/templates/shopyo_auth/emails/activate_user.txt
shopyo_auth/templates/shopyo_auth/emails/reset_password.html
shopyo_auth/templates/shopyo_auth/emails/reset_password.txt
shopyo_auth-1.5.0.dist-info/METADATA
shopyo_auth-1.5.0.dist-info/WHEEL
shopyo_auth-1.5.0.dist-info/top_level.txt
shopyo_auth-1.5.0.dist-info/RECORD
